Workbook
Name _Hlk214034626: Sheet3!$A$157

Sheet Sheet1
A1: NO | B1: SPRINT | C1: ACTIVITY | D1: START DATE | E1: DUE DATE | F1: DURATION (Days) | G1: BOBOT (%) | H1: STATUS | I1: M1 | J1: M2 | K1: M3 | L1: M4 | M1: M5 | N1: M6 | O1: M7 | P1: M8 | Q1: M9 | R1: M10 | S1: M11 | T1: M12 | U1: M13 | V1: M14 | W1: M15 | X1: M16 | Y1: M17 | Z1: M18
A2: 1 | B2: Sprint 0 | C2: Identifikasi Kebutuhan Sistem (Wawancara, Observasi, Analisis Masalah) | D2: 06/11/2023 | E2: 10/11/2023 | F2: 5 | G2: 1.45 | H2: Done | I2: 1.45
A3: 2 | B3: Sprint 0 | C3: Mencari Studi Pustaka sebagai referensi | D3: 13/11/2023 | E3: 24/04/2024 | F3: 105 | G3: 30.43 | H3: Done | J3: 3.04 | K3: 3.04 | L3: 3.04 | M3: 3.04 | N3: 3.04 | O3: 3.04 | P3: 3.04 | Q3: 3.04 | R3: 6.15
A4: 3 | B4: Sprint 0 | C4: Perancangan Alur Sistem (Flowchart, UML) | D4: 25/04/2024 | E4: 29/05/2024 | F4: 20 | G4: 5.80 | H4: Done | N4: 2.90 | O4: 2.90
A5: 4 | B5: Sprint 0 | C5: Perancangan Database (Normalisasi, ERD, LRS, Spesifikasi Database) | D5: 30/05/2024 | E5: 12/07/2024 | F5: 30 | G5: 8.70 | H5: Done | O5: 2.90 | P5: 2.90 | Q5: 2.90
A6: 5 | B6: Sprint 0 | C6: Perancangan UI | D6: 15/07/2024 | E6: 23/08/2024 | F6: 30 | G6: 8.70 | H6: Done | Q6: 2.90 | R6: 5.80
A7: 6 | B7: Sprint 0 | C7: Perancangan Product Backlog | D7: 26/08/2024 | E7: 02/09/2024 | F7: 6 | G7: 1.74 | H7: Done | R7: 0.87 | S7: 0.87
A10: 1 | B10: Sprint 1 | C10: Pembuatan Database, Tabel Akses, User, dan Level | D10: 03/09/2024 | E10: 03/09/2024 | F10: 1 | G10: 0.29 | H10: Done | S10: 0.29
A11: 2 | B11: Sprint 1 | C11: Pembuatan UI Login | D11: 04/09/2024 | E11: 10/09/2024 | F11: 5 | G11: 1.45 | H11: Done | S11: 1.45
A12: 3 | B12: Sprint 1 | C12: Implementasi autentikasi | D12: 11/09/2024 | E12: 18/09/2024 | F12: 5 | G12: 1.45 | H12: Done | S12: 1.45
A13: 4 | B13: Sprint 1 | C13: Pembuatan Menu logout | D13: 19/09/2024 | E13: 19/09/2024 | F13: 1 | G13: 0.29 | H13: Done | S13: 0.29
A14: 5 | B14: Sprint 1 | C14: Pembuatan tampilan dashboard | D14: 20/09/2024 | E14: 26/09/2024 | F14: 5 | G14: 1.45 | H14: Done | S14: 1.45
A15: 6 | B15: Sprint 1 | C15: Blackbox Testing Sprint 1 | D15: 27/09/2024 | E15: 30/09/2024 | F15: 2 | G15: 0.58 | H15: Done | S15: 0.58
A16: 7 | B16: Sprint 1 | C16: UAT, Review & Retrospective | D16: 01/10/2024 | E16: 03/10/2024 | F16: 2 | G16: 0.58 | H16: Done | T16: 0.58
A18: 1 | B18: Sprint 2 | C18: Pembuatan Tabel Database Customer | D18: 03/10/2024 | E18: 03/10/2024 | F18: 1 | G18: 0.29 | H18: Done | T18: 0.29
A19: 2 | B19: Sprint 2 | C19: Pembuatan UI Halaman Customer | D19: 04/10/2024 | E19: 10/10/2024 | F19: 5 | G19: 1.45 | H19: Done | T19: 1.45
A20: 3 | B20: Sprint 2 | C20: Implementasi Backend (CRUD) Modul Customer | D20: 11/10/2024 | E20: 17/10/2024 | F20: 5 | G20: 1.45 | H20: Done | T20: 1.45
A21: 4 | B21: Sprint 2 | C21: Pembuatan UI Halaman User | D21: 18/10/2024 | E21: 24/10/2024 | F21: 5 | G21: 1.45 | H21: Done | T21: 1.45
A22: 5 | B22: Sprint 2 | C22: Implementasi Backend (CRUD) Modul User | D22: 25/10/2024 | E22: 31/10/2024 | F22: 5 | G22: 1.45 | H22: Done | T22: 1.45
A24: 1 | B24: Sprint 3 | C24: Pembuatan Tabel Database Project | D24: 01/11/2024 | E24: 01/11/2024 | F24: 1 | G24: 0.29 | H24: Done | T24: 0.29
A25: 2 | B25: Sprint 3 | C25: Pembuatan UI Halaman Project | D25: 04/11/2024 | E25: 08/11/2024 | F25: 5 | G25: 1.45 | H25: Done | T25: 1.45
A26: 3 | B26: Sprint 3 | C26: Implementasi Backend (CRUD) Modul Project | D26: 11/11/2024 | E26: 15/11/2024 | F26: 5 | G26: 1.45 | H26: Done | T26: 1.45
A27: 4 | B27: Sprint 3 | C27: Pembuatan UI Upload & Parsing File MS Project | D27: 18/11/2024 | E27: 22/11/2024 | F27: 5 | G27: 1.45 | H27: Done | U27: 1.45
A28: 5 | B28: Sprint 3 | C28: Implementasi Backend Parsing File MS Project | D28: 25/11/2024 | E28: 29/11/2024 | F28: 5 | G28: 1.45 | H28: Done | U28: 1.45
A29: 6 | B29: Sprint 3 | C29: Blackbox Testing Sprint 3 | D29: 02/12/2024 | E29: 06/12/2024 | F29: 5 | G29: 1.45 | H29: Done | U29: 1.45
A30: 7 | B30: Sprint 3 | C30: UAT, Review & Retrospective | D30: 09/12/2024 | E30: 13/12/2024 | F30: 5 | G30: 1.45 | H30: Done | U30: 1.45
A32: 1 | B32: Sprint 4 | C32: Pembuatan Tabel Database EVM (PV, EV, AC) | D32: 16/12/2024 | E32: 20/12/2024 | F32: 5 | G32: 1.45 | H32: Done | U32: 1.45
A33: 2 | B33: Sprint 4 | C33: Implementasi Perhitungan PV (Planned Value) | D33: 23/12/2024 | E33: 27/12/2024 | F33: 5 | G33: 1.45 | H33: Done | U33: 1.45
A34: 3 | B34: Sprint 4 | C34: Implementasi Perhitungan EV (Earned Value) | D34: 30/12/2024 | E34: 03/01/2025 | F34: 5 | G34: 1.45 | H34: Done | V34: 1.45
A35: 4 | B35: Sprint 4 | C35: Implementasi Perhitungan AC (Actual Cost) | D35: 06/01/2025 | E35: 10/01/2025 | F35: 5 | G35: 1.45 | H35: Done | V35: 1.45
A36: 5 | B36: Sprint 4 | C36: Implementasi Perhitungan SV, CV, SPI, CPI | D36: 13/01/2025 | E36: 17/01/2025 | F36: 5 | G36: 1.45 | H36: Done | V36: 1.45
A37: 6 | B37: Sprint 4 | C37: Pembuatan UI Dashboard EVM | D37: 20/01/2025 | E37: 24/01/2025 | F37: 5 | G37: 1.45 | H37: Done | V37: 1.45
A38: 7 | B38: Sprint 4 | C38: Blackbox Testing Sprint 4 | D38: 27/01/2025 | E38: 31/01/2025 | F38: 5 | G38: 1.45 | H38: Done | V38: 1.45
A40: 1 | B40: Sprint 5 | C40: Implementasi Real-time Update Progress | D40: 03/02/2025 | E40: 07/02/2025 | F40: 5 | G40: 1.45 | H40: Done | W40: 1.45
A41: 2 | B41: Sprint 5 | C41: Pembuatan Grafik Kurva S | D41: 10/02/2025 | E41: 14/02/2025 | F41: 5 | G41: 1.45 | H41: Done | W41: 1.45
A42: 3 | B42: Sprint 5 | C42: Implementasi Alert & Notifikasi | D42: 17/02/2025 | E42: 21/02/2025 | F42: 5 | G42: 1.45 | H42: Done | W42: 1.45
A43: 4 | B43: Sprint 5 | C43: Pembuatan Report Generator | D43: 24/02/2025 | E43: 28/02/2025 | F43: 5 | G43: 1.45 | H43: Done | W43: 1.45
A44: 5 | B44: Sprint 5 | C44: Blackbox Testing Sprint 5 | D44: 03/03/2025 | E44: 07/03/2025 | F44: 5 | G44: 1.45 | H44: Done | X44: 1.45
A46: 1 | B46: Sprint 6 | C46: Integration Testing Seluruh Modul | D46: 10/03/2025 | E46: 14/03/2025 | F46: 5 | G46: 1.45 | H46: Done | X46: 1.45
A47: 2 | B47: Sprint 6 | C47: User Acceptance Testing (UAT) Lengkap | D47: 17/03/2025 | E47: 21/03/2025 | F47: 5 | G47: 1.45 | H47: Done | X47: 1.45
A48: 3 | B48: Sprint 6 | C48: Perbaikan Bug & Enhancement | D48: 24/03/2025 | E48: 28/03/2025 | F48: 5 | G48: 1.45 | H48: Done | X48: 1.45
A49: 4 | B49: Sprint 6 | C49: Deployment ke Server Production | D49: 31/03/2025 | E49: 04/04/2025 | F49: 5 | G49: 1.45 | H49: Done | Y49: 1.45
A50: 5 | B50: Sprint 6 | C50: Dokumentasi Sistem & User Manual | D50: 07/04/2025 | E50: 11/04/2025 | F50: 5 | G50: 1.45 | H50: Done | Y50: 1.45
A54: 1 | B54: Penyusunan Laporan | C54: Penyusunan Bab 1 - Pendahuluan | D54: 14/04/2025 | E54: 18/04/2025 | F54: 5 | G54: 1.16 | H54: Done | Y54: 1.16
A55: 2 | B55: Penyusunan Laporan | C55: Penyusunan Bab 2 - Landasan Teori | D55: 21/04/2025 | E55: 25/04/2025 | F55: 5 | G55: 1.16 | H55: Done | Y55: 1.16
A56: 3 | B56: Penyusunan Laporan | C56: Penyusunan Bab 3 - Metodologi | D56: 28/04/2025 | E56: 02/05/2025 | F56: 5 | G56: 1.16 | H56: Done | Z56: 1.16
A57: 4 | B57: Penyusunan Laporan | C57: Penyusunan Bab 4 - Hasil & Pembahasan | D57: 05/05/2025 | E57: 09/05/2025 | F57: 5 | G57: 1.16 | H57: Done | Z57: 1.16
A58: 5 | B58: Penyusunan Laporan | C58: Penyusunan Bab 5 - Kesimpulan & Saran | D58: 12/05/2025 | E58: 16/05/2025 | F58: 5 | G58: 1.16 | H58: Done | Z58: 1.16
A59: 6 | B59: Penyusunan Laporan | C59: Revisi & Finalisasi Laporan | D59: 19/05/2025 | E59: 23/05/2025 | F59: 5 | G59: 1.16 | H59: Done | Z59: 1.16
E60: Total | F60: =SUM(F2:F59) -> 384
A62: MONTH | B62: PLAN (%) | C62: ACTUAL (%) | D62: CUMULATIVE PLAN (%) | E62: CUMULATIVE ACTUAL (%)
A63: M1 | B63: 1.45 | C63: 1.45 | D63: 1.45 | E63: 1.45
A64: M2 | B64: 3.04 | C64: 3.04 | D64: 4.49 | E64: 4.49
A65: M3 | B65: 3.04 | C65: 3.04 | D65: 7.53 | E65: 7.53
A66: M4 | B66: 3.04 | C66: 3.04 | D66: 10.57 | E66: 10.57
A67: M5 | B67: 3.04 | C67: 3.04 | D67: 13.61 | E67: 13.61
A68: M6 | B68: 5.94 | C68: 5.94 | D68: 19.55 | E68: 19.55
A69: M7 | B69: 5.94 | C69: 5.94 | D69: 25.49 | E69: 25.49
A70: M8 | B70: 2.90 | C70: 2.90 | D70: 28.39 | E70: 28.39
A71: M9 | B71: 5.80 | C71: 5.80 | D71: 34.19 | E71: 34.19
A72: M10 | B72: 6.67 | C72: 6.67 | D72: 40.86 | E72: 40.86
A73: M11 | B73: 5.51 | C73: 5.51 | D73: 46.37 | E73: 46.37
... A83: SPRINT | B83: JUMLAH TASK | C83: BOBOT (%) | D83: STATUS | E83: SELESAI
A84: Sprint 0 | B84: 6 | C84: 56.82 | D84: Done | E84: 1
A85: Sprint 1 | B85: 7 | C85: 6.09 | D85: Done | E85: 1
A86: Sprint 2 | B86: 5 | C86: 7.09 | D86: Done | E86: 1
A87: Sprint 3 | B87: 7 | C87: 10.15 | D87: Done | E87: 1
A88: Sprint 4 | B88: 7 | C88: 10.15 | D88: Done | E88: 1
A89: Sprint 5 | B89: 5 | C89: 7.25 | D89: Done | E89: 1
A90: Sprint 6 | B90: 5 | C90: 7.25 | D90: Done | E90: 1
A91: Laporan | B91: 6 | C91: 6.96 | D91: Done | E91: 1
A92: TOTAL | B92: 48 | C92: 100.00 | D92: Done | E92: 1
A95: METRIK | B95: NILAI | C95: KETERANGAN
A96: PV (Planned Value) | B96: 1 | C96: Total rencana biaya/pekerjaan
A97: EV (Earned Value) | B97: 1 | C97: Total pekerjaan yang diselesaikan
A98: AC (Actual Cost) | B98: 1 | C98: Total biaya aktual yang dikeluarkan
A99: SV (Schedule Variance) | B99: 0 | C99: EV - PV = Tepat Waktu
A100: CV (Cost Variance) | B100: 0 | C100: EV - AC = Sesuai Budget
A101: SPI (Schedule Performance Index) | B101: 1.00 | C101: Kinerja jadwal sempurna
A102: CPI (Cost Performance Index) | B102: 1.00 | C102: Kinerja biaya sempurna

Sheet master
A1: NO | B1: SPRINT | C1: ACTIVITY | D1: START DATE | E1: END DATE | F1: DURATION (days) | G1: WEIGHT (%) | H1: STATUS
A2: 1. | B2: Sprint 0 | C2: Identifikasi Kebutuhan Sistem (Wawancara, Observasi, Analisis Masalah) | D2: 45236 | E2: 45240 | F2: 5 | G2: =F2/F8 -> 0.016891892 | H2: To do
A3: 2. | B3: Sprint 0 | C3: Mencari Studi Pustaka sebagai referensi | D3: 45243 | E3: 45406 | F3: 164 | G3: =F3/F8 -> 0.55405405 | H3: To do
A4: 3. | B4: Sprint 0 | C4: Perancangan Alur Sistem (Flowchart, UML) | D4: 45407 | E4: 45441 | F4: 35 | G4: =F4/F8 -> 0.11824324 | H4: To do
A5: 4. | B5: Sprint 0 | C5: Perancangan Database (Normalisasi, ERD, LRS, Spesifikasi Database) | D5: 45442 | E5: 45485 | F5: 44 | G5: =F5/F8 -> 0.14864865 | H5: To do
A6: 5. | B6: Sprint 0 | C6: Perancangan UI | D6: 45488 | E6: 45527 | F6: 40 | G6: =F6/F8 -> 0.13513514 | H6: To do
A7: 6. | B7: Sprint 0 | C7: Perancangan Product Backlog | D7: 45530 | E7: 45537 | F7: 8 | G7: =F7/F8 -> 0.027027027 | H7: To do
B8: TOTAL DURATION SPRINT-0 | D8: 45236 | E8: 45537 | F8: 296
B9: CONTRIBUTE SPRINT-0 | G9: =F8/F61 -> 0.60040568
A10: 1. | B10: Sprint 1 | C10: Pembuatan Database, Tabel Akses, User, dan Level | D10: 45538 | E10: 45538 | F10: 1 | G10: =F10/F17 -> 0.032258065 | H10: To do
A11: 2. | B11: Sprint 1 | C11: Pembuatan UI Login | D11: 45539 | E11: 45545 | F11: 7 | G11: =F11/F17 -> 0.22580645 | H11: To do
A12: 3. | B12: Sprint 1 | C12: Implementasi autentikasi | D12: 45546 | E12: 45553 | F12: 8 | G12: =F12/F17 -> 0.25806452 | H12: To do
A13: 4. | B13: Sprint 1 | C13: Pembuatan Menu logout | D13: 45554 | E13: 45554 | F13: 1 | G13: =F13/F17 -> 0.032258065 | H13: To do
A14: 5. | B14: Sprint 1 | C14: Pembuatan tampilan dashboard | D14: 45555 | E14: 45561 | F14: 7 | G14: =F14/F17 -> 0.22580645 | H14: To do
A15: 6. | B15: Sprint 1 | C15: Blackbox Testing Sprint 1 | D15: 45562 | E15: 45565 | F15: 4 | G15: =F15/F17 -> 0.12903226 | H15: To do
A16: 7. | B16: Sprint 1 | C16: UAT, Review dan Retrospective | D16: 45566 | E16: 45568 | F16: 3 | G16: =F16/F17 -> 0.096774194 | H16: To do
C17: TOTAL DURATION SPRINT-1 | D17: 45538 | E17: 45568 | F17: =SUM(F10:F16) -> 31
C18: CONTRIBUTE SPRINT-1 | G18: =F17/F61 -> 0.062880325
A19: 1. | B19: Sprint 2 | C19: Pembuatan Tabel Database Client | D19: 45568 | E19: 45568 | F19: 1 | G19: =F19/F24 -> 0.034482759 | H19: To do
A20: 2. | B20: Sprint 2 | C20: Pembuatan UI Halaman Client | D20: 45569 | E20: 45575 | F20: 7 | G20: =F20/F24 -> 0.24137931 | H20: To do
A21: 3. | B21: Sprint 2 | C21: Implementasi Backend (CRUD) Modul Client | D21: 45576 | E21: 45582 | F21: 7 | G21: =F21/F24 -> 0.24137931 | H21: To do
A22: 4. | B22: Sprint 2 | C22: Pembuatan UI Halaman User | D22: 45583 | E22: 45589 | F22: 7 | G22: =F22/F24 -> 0.24137931 | H22: To do
A23: 5. | B23: Sprint 2 | C23: Implementasi Backend (CRUD) Modul User | D23: 45590 | E23: 45596 | F23: 7 | G23: =F23/F24 -> 0.24137931 | H23: To do
C24: TOTAL DURATION SPRINT-2 | D24: 45568 | E24: 45596 | F24: =SUM(F19:F23) -> 29
C25: CONTRIBUTE SPRINT-2 | G25: =F24/F61 -> 0.058823529
A26: 1. | B26: Sprint 3 | C26: Pembuatan Tabel Database Project | D26: 45597 | E26: 45597 | F26: 1 | G26: =F26/F37 -> 0.024390244 | H26: To do
A27: 2. | B27: Sprint 3 | C27: Pembuatan UI Halaman Project | D27: 45600 | E27: 45604 | F27: 5 | G27: =F27/F37 -> 0.12195122 | H27: To do
A28: 3. | B28: Sprint 3 | C28: Implementasi Backend (CRUD) Modul Project | D28: 45607 | E28: 45611 | F28: 5 | G28: =F28/F37 -> 0.12195122 | H28: To do
A29: 4. | B29: Sprint 3 | C29: Pembuatan UI Task dan sub Task | D29: 45614 | E29: 45618 | F29: 5 | G29: =F29/F37 -> 0.12195122 | H29: To do
A30: 5. | B30: Sprint 3 | C30: Implementasi Backend (CRUD) Modul Task | D30: 45621 | E30: 45625 | F30: 5 | G30: =F30/F37 -> 0.12195122 | H30: To do
A31: 6. | B31: Sprint 3 | C31: Pembuatan UI Halaman Inventories | D31: 45628 | E31: 45629 | F31: 2 | G31: =F31/F37 -> 0.048780488 | H31: To do
A32: 7. | B32: Sprint 3 | C32: Implementasi Backend (CRUD) Modul Inventories | D32: 45630 | E32: 45632 | F32: 3 | G32: =F32/F37 -> 0.073170732 | H32: To do
A33: 8. | B33: Sprint 3 | C33: Pembuatan UI Halaman Work Report | D33: 45635 | E33: 45636 | F33: 2 | G33: =F33/F37 -> 0.048780488 | H33: To do
A34: 9. | B34: Sprint 3 | C34: Implementasi Backend (CRUD) Modul Work Report | D34: 45637 | E34: 45639 | F34: 3 | G34: =F34/F37 -> 0.073170732 | H34: To do
A35: 10. | B35: Sprint 3 | C35: Blackbox Testing Sprint 3 | D35: 45628 | E35: 45632 | F35: 5 | G35: =F35/F37 -> 0.12195122 | H35: To do
A36: 11. | B36: Sprint 3 | C36: UAT, Review dan Retrospective | D36: 45635 | E36: 45639 | F36: 5 | G36: =F36/F37 -> 0.12195122 | H36: To do
C37: TOTAL DURATION SPRINT-3 | D37: 45597 | E37: 45639 | F37: =SUM(F26:F36) -> 41
C38: CONTRIBUTE SPRINT-3 | G38: =F37/F61 -> 0.0831643
A39: 1. | B39: Sprint 4 | C39: Pembuatan Tabel Database EVM (PV, EV, AC) | D39: 45642 | E39: 45646 | F39: 5 | G39: =F39/F46 -> 0.14285714 | H39: To do
A40: 2. | B40: Sprint 4 | C40: Implementasi Perhitungan PV (Planned Value) | D40: 45649 | E40: 45653 | F40: 5 | G40: =F40/F46 -> 0.14285714 | H40: To do
A41: 3. | B41: Sprint 4 | C41: Implementasi Perhitungan EV (Earned Value) | D41: 45656 | E41: 45660 | F41: 5 | G41: =F41/F46 -> 0.14285714 | H41: To do
A42: 4. | B42: Sprint 4 | C42: Implementasi Perhitungan AC (Actual Cost) | D42: 45663 | E42: 45667 | F42: 5 | G42: =F42/F46 -> 0.14285714 | H42: To do
A43: 5. | B43: Sprint 4 | C43: Implementasi Perhitungan SV, CV, SPI, CPI | D43: 45670 | E43: 45674 | F43: 5 | G43: =F43/F46 -> 0.14285714 | H43: To do
A44: 6. | B44: Sprint 4 | C44: Pembuatan UI Dashboard EVM | D44: 45677 | E44: 45681 | F44: 5 | G44: =F44/F46 -> 0.14285714 | H44: To do
A45: 7. | B45: Sprint 4 | C45: Blackbox Testing Sprint 4 | D45: 45684 | E45: 45688 | F45: 5 | G45: =F45/F46 -> 0.14285714 | H45: To do
C46: TOTAL DURATION SPRINT-4 | D46: 45642 | E46: 45688 | F46: =SUM(F39:F45) -> 35
C47: CONTRIBUTE SPRINT-4 | G47: =F46/F61 -> 0.070993915
A48: 1. | B48: Sprint 5 | C48: Implementasi Real-time Update Progress | D48: 45691 | E48: 45695 | F48: 5 | G48: =F48/F52 -> 0.25 | H48: To do
A49: 2. | B49: Sprint 5 | C49: Pembuatan Grafik Kurva S | D49: 45698 | E49: 45702 | F49: 5 | G49: =F49/F52 -> 0.25 | H49: To do
A50: 3. | B50: Sprint 5 | C50: Implementasi Alert dan Notifikasi | D50: 45705 | E50: 45709 | F50: 5 | G50: =F50/F52 -> 0.25 | H50: To do
A51: 5. | B51: Sprint 5 | C51: Blackbox Testing Sprint 5 | D51: 45719 | E51: 45723 | F51: 5 | G51: =F51/F52 -> 0.25 | H51: To do
C52: TOTAL DURATION SPRINT-5 | D52: 45691 | E52: 45723 | F52: =SUM(F48:F51) -> 20
C53: CONTRIBUTE SPRINT-5 | G53: =F52/F61 -> 0.040567951
A54: 1. | B54: Sprint 6 | C54: Integration Testing Seluruh Modul | D54: 45726 | E54: 45730 | F54: 5 | G54: =F54/F59 -> 0.12195122 | H54: To do
A55: 2. | B55: Sprint 6 | C55: User Acceptance Testing (UAT) Lengkap | D55: 45733 | E55: 45737 | F55: 5 | G55: =F55/F59 -> 0.12195122 | H55: To do
A56: 3. | B56: Sprint 6 | C56: Perbaikan Bug dan Enhancement | D56: 45740 | E56: 45744 | F56: 5 | G56: =F56/F59 -> 0.12195122 | H56: To do
A57: 4. | B57: Sprint 6 | C57: Deployment ke Server Production | D57: 45747 | E57: 45751 | F57: 5 | G57: =F57/F59 -> 0.12195122 | H57: To do
A58: 5. | B58: Sprint 6 | C58: Dokumentasi Sistem dan User Manual | D58: 45754 | E58: 45775 | F58: 21 | G58: =F58/F59 -> 0.51219512 | H58: To do
C59: TOTAL DURATION SPRINT-6 | D59: 45726 | E59: =E58 -> 45775 | F59: =SUM(F54:F58) -> 41
C60: CONTRIBUTE SPRINT-6 | G60: =F59/F61 -> 0.0831643
C61: TOTAL DURATION SPRINT 0-6 | F61: =SUM(F59,F52,F46,F37,F24,F17,F8) -> 493
C62: TOTAL WEIGHT SPRINT 0-6 | G62: =SUM(G9,G18,G25,G38,G47,G53,G60) -> 1
C63: MONTH(30,44) | F63: =F61/30.44 -> 16.195795
A65: No | B65: Month | C65: Start Date | D65: End Date | E65: Days | F65: Plan (%) | G65: Cumulative Plan (%) | H65: PV | I65: EV | J65: SV
A66: 1. | B66: M1 | C66: 45236 | D66: 45260 | E66: 25 | F66: 5.08 | G66: 5.08 | H66: 5.08 | I66: 5.08 | J66: =I66-H66 -> 0
A67: 2. | B67: M2 | C67: 45261 | D67: 45291 | E67: 31 | F67: 6.3 | G67: 11.38 | H67: 11.38 | I67: 11.38 | J67: =I67-H67 -> 0
A68: 3. | B68: M3 | C68: 45292 | D68: 45322 | E68: 31 | F68: 6.3 | G68: 17.68 | H68: 17.68 | I68: 17.68 | J68: =I68-H68 -> 0
A69: 4. | B69: M4 | C69: 45323 | D69: 45351 | E69: 29 | F69: 5.89 | G69: 23.57 | H69: 23.57 | I69: 23.57 | J69: =I69-H69 -> 0
A70: 5. | B70: M5 | C70: 45352 | D70: 45382 | E70: 31 | F70: 6.3 | G70: 29.87 | H70: 29.87 | I70: 29.87 | J70: =I70-H70 -> 0
A71: 6. | B71: M6 | C71: 45383 | D71: 45412 | E71: 30 | F71: 6.1 | G71: 35.97 | H71: 35.97 | I71: 35.97 | J71: =I71-H71 -> 0
A72: 7. | B72: M7 | C72: 45413 | D72: 45443 | E72: 31 | F72: 6.3 | G72: 42.27 | H72: 42.27 | I72: 42.27 | J72: =I72-H72 -> 0
A73: 8. | B73: M8 | C73: 45444 | D73: 45473 | E73: 30 | F73: 6.1 | G73: 48.37 | H73: 48.37 | I73: 48.37 | J73: =I73-H73 -> 0
A74: 9. | B74: M9 | C74: 45474 | D74: 45504 | E74: 31 | F74: 6.3 | G74: 54.67 | H74: 54.67 | I74: 54.67 | J74: =I74-H74 -> 0
A75: 10. | B75: M10 | C75: 45505 | D75: 45535 | E75: 31 | F75: 6.3 | G75: 60.97 | H75: 60.97 | I75: 60.97 | J75: =I75-H75 -> 0
A76: 11. | B76: M11 | C76: 45536 | D76: 45565 | E76: 30 | F76: 6.13 | G76: 67.1 | H76: 67.1 | I76: 67.1 | J76: =I76-H76 -> 0
A77: 12. | B77: M12 | C77: 45566 | D77: 45596 | E77: 31 | F77: 6.22 | G77: 73.32 | H77: 73.32 | I77: 73.32 | J77: =I77-H77 -> 0
... A82: 17. | B82: M17 | C82: 45717 | D82: 45775 | E82: 59 | F82: 2.73 | G82: 100 | H82: 100 | I82: 100 | J82: =I82-H82 -> 0

Sheet hasil sprint 0-6
A1: Sprint | B1: Total story sprint | C1: Start Date | D1: End Date | E1: Duration | F1: Weight (%) | G1: PV | H1: EV | I1: SV | J1: Status
A2: Sprint 0 | B2: 6 | C2: 45236 | D2: 45537 | E2: =master!F8 -> 296 | F2: =E2/E9 -> 0.60040568 | G2: =F2/F9 -> 0.60040568 | H2: =G2/F9 -> 0.60040568 | I2: =H2-G2 -> 0 | J2: Done
A3: Sprint 1 | B3: 8 | C3: 45538 | D3: 45568 | E3: =master!F17 -> 31 | F3: =E3/E9 -> 0.062880325 | G3: =G2+F3 -> 0.663286 | H3: =H2+F3 -> 0.663286 | I3: =H3-G3 -> 0 | J3: Done
A4: Sprint 2 | B4: 5 | C4: 45568 | D4: 45596 | E4: =master!F24 -> 29 | F4: =E4/E9 -> 0.058823529 | G4: =G3+F4 -> 0.72210953 | H4: =H3+F4 -> 0.72210953 | I4: =H4-G4 -> 0 | J4: Done
A5: Sprint 3 | B5: 11 | C5: 45597 | D5: 45639 | E5: =master!F37 -> 41 | F5: =E5/E9 -> 0.0831643 | G5: =G4+F5 -> 0.80527383 | H5: =H4+F5 -> 0.80527383 | I5: =H5-G5 -> 0 | J5: Done
A6: Sprint 4 | B6: 7 | C6: 45642 | D6: 45688 | E6: =master!F46 -> 35 | F6: =E6/E9 -> 0.070993915 | G6: =G5+F6 -> 0.87626775 | H6: =H5+F6 -> 0.87626775 | I6: =H6-G6 -> 0 | J6: To do
A7: Sprint 5 | B7: 5 | C7: 45691 | D7: 45723 | E7: =master!F52 -> 20 | F7: =E7/E9 -> 0.040567951 | G7: =G6+F7 -> 0.9168357 | H7: =H6+F7 -> 0.9168357 | I7: =H7-G7 -> 0 | J7: To do
A8: Sprint 6 | B8: 5 | C8: 45726 | D8: 45980 | E8: =master!F59 -> 41 | F8: =E8/E9 -> 0.0831643 | G8: =G7+F8 -> 1 | H8: =H7+F8 -> 1 | I8: =H8-G8 -> 0 | J8: To do
B9: TOTAL | E9: =master!F61 -> 493 | F9: =SUM(F2:F8) -> 1

Sheet Sheet3
A1: No | B1: Nama Field | C1: Tipe Data | D1: Lebar | E1: Keterangan
A2: 1. | B2: Id | C2: bigint | D2: - | E2: Primary Key sebagai identitas unik setiap user. Auto increment.
A3: 2. | B3: name | C3: varchar | D3: 50 | E3: Nama lengkap pengguna yang digunakan untuk identifikasi di aplikasi. Tidak boleh kosong.
A4: 3. | B4: email | C4: varchar | D4: 20 | E4: Alamat email pengguna sebagai identitas login. Harus unik dan tidak boleh kosong.
A5: 4. | B5: email_verified_at | C5: timestamp | D5: - | E5: Menyimpan waktu verifikasi email. Nilai NULL berarti email belum diverifikasi.
A6: 5. | B6: password | C6: varchar | D6: 50 | E6: Menyimpan password yang sudah di-hash. Tidak disimpan dalam bentuk teks asli. Wajib diisi.
A7: 6. | B7: avatar | C7: varchar | D7: 125 | E7: Menyimpan nama file atau path gambar profil pengguna. Boleh kosong.
A8: 7. | B8: phone | C8: varchar | D8: 20 | E8: Nomor telepon pengguna. Tidak wajib diisi.
A9: 8. | B9: job_title | C9: varchar | D9: 50 | E9: Jabatan atau posisi pekerjaan user di dalam organisasi/proyek. Tidak wajib diisi.
A10: 9. | B10: address | C10: varchar | D10: 125 | E10: Alamat tempat tinggal pengguna. Bersifat opsional.
A12: No | B12: Nama Field | C12: Tipe Data | D12: Lebar | E12: Keterangan
A13: 1. | B13: Id | C13: bigint | D13: - | E13: Primary key dari tabel roles yang berfungsi sebagai identitas unik setiap peran (role) dalam sistem. Nilai id bersifat auto-increment sehingga setiap role baru akan mendapatkan nomor identitas yang berbeda secara otomatis. Field ini digunakan sebagai acuan relasi pada tabel pivot seperti role_has_permissions dan model_has_roles.
A14: 2. | B14: Name | C14: varchar | D14: 50 | E14: Menyimpan nama peran (role) dalam sistem, seperti admin, project_manager, atau team_member. Field ini berfungsi sebagai identitas utama role dan bersifat unik. Role digunakan untuk mengelompokkan hak akses pada pengguna. Wajib diisi.
A15: 3. | B15: Guard_name | C15: varchar | D15: 50 | E15: Menentukan guard atau mekanisme autentikasi yang digunakan untuk role tersebut. Secara umum nilainya adalah web atau api. Guard memastikan bahwa role hanya berlaku pada konteks autentikasi tertentu. Wajib diisi.
A18: No | B18: Nama Field | C18: Tipe Data | D18: Lebar | E18: Keterangan
A19: 1. | B19: Id | C19: bigint | D19: - | E19: Primary key dari tabel permissions yang menjadi identitas unik untuk setiap hak akses (permission).Nilai id bersifat auto-increment dan digunakan sebagai referensi utama dalam relasi many-to-many melalui tabel pivot role_has_permissions dan model_has_permissions.
A20: 2. | B20: Name | C20: varchar | D20: 50 | E20: Menyimpan nama permission atau hak akses spesifik, seperti create project, edit task, view report, atau delete user. Permission merepresentasikan aksi yang diperbolehkan pada sistem. Field ini harus unik dan wajib diisi.
A21: 3. | B21: Guard_name | C21: varchar | D21: 50 | E21: Menentukan guard atau konteks autentikasi tempat permission diterapkan. Guard memastikan bahwa permission tidak bercampur antara jenis autentikasi yang berbeda. Wajib diisi.
A23: No | B23: Nama Field | C23: Tipe Data | D23: Lebar | E23: Keterangan
A24: 1. | B24: Id | C24: bigint | D24: - | E24: Primary key perusahaan pemilik (owner company). Bersifat auto-increment
A25: 2. | B25: Name | C25: varchar | D25: 50 | E25: Nama resmi perusahaan pemilik yang dicatat dalam sistem. Wajib
A26: 3. | B26: Logo | C26: Varchar | D26: 125 | E26: Menyimpan nama file atau path dari logo perusahaan. Opsional
A27: 4. | B27: Address | C27: Varchar | D27: 125 | E27: Alamat lengkap perusahaan pemilik. Isian ini membantu identifikasi lokasi fisik perusahaan. Opsional.
A28: 5. | B28: Postal_code | C28: Int | D28: 20 | E28: Kode pos area lokasi perusahaan untuk memudahkan proses kategorisasi wilayah atau pengiriman dokumen. Opsional.
A29: 6. | B29: City | C29: Varchar | D29: 20 | E29: Nama kota tempat perusahaan berada. Digunakan untuk kebutuhan administratif dan grouping data. Opsional.
A30: 7. | B30: Email | C30: Varchar | D30: 20 | E30: Alamat email resmi perusahaan. Digunakan untuk komunikasi terkait proyek atau notifikasi sistem. Opsional.
A31: 8. | B31: Phone | C31: Varchar | D31: 20 | E31: Nomor telepon perusahaan. Dipakai untuk informasi kontak dan validasi data perusahaan. Opsional.
A32: 9. | B32: Web | C32: Varchar | D32: 125 | E32: URL website resmi perusahaan. Opsional dan digunakan sebagai informasi tambahan profil perusahaan.
A34: No | B34: Nama Field | C34: Tipe Data | D34: Lebar | E34: Keterangan
A35: 1. | B35: User_Id | C35: bigint | D35: - | E35: Foreign key yang merujuk pada id di tabel users. Digunakan untuk menghubungkan pengguna dengan perusahaan klien. Mewakili pengguna yang diberi akses atau berkaitan dengan perusahaan klien tertentu.
A36: 2. | B36: Client_company_Id | C36: bigint | D36: - | E36: Foreign key yang merujuk pada id di tabel client_companies. Menandai perusahaan klien yang terasosiasi dengan user tertentu. Berfungsi sebagai relasi many-to-many antara user dan perusahaan klien.
A39: No | B39: Nama Field | C39: Tipe Data | D39: Lebar | E39: Keterangan
A40: 1. | B40: Id | C40: bigint | D40: - | E40: Primary key Perusahaan Clients. Bersifat auto-increment
A41: 2. | B41: name | C41: varchar | D41: 50 | E41: Nama resmi perusahaan Client yang dicatat dalam sistem. Wajib
A42: 3. | B42: Logo | C42: Varchar | D42: 125 | E42: Menyimpan nama file atau path dari logo perusahaan. Opsional
A43: 4. | B43: Address | C43: Varchar | D43: 125 | E43: Alamat lengkap Perusahaan Clients. Isian ini membantu identifikasi lokasi fisik perusahaan. Opsional.
A44: 5. | B44: Postal_code | C44: Int | D44: 20 | E44: Kode pos area lokasi perusahaan. Memudahkan proses kategorisasi wilayah atau pengiriman dokumen. Opsional.
A45: 6. | B45: city | C45: Varchar | D45: 20 | E45: Nama kota tempat perusahaan berada. Digunakan untuk kebutuhan administratif dan grouping data. Opsional.
A46: 7. | B46: email | C46: Varchar | D46: 20 | E46: Alamat email resmi perusahaan. Digunakan untuk komunikasi terkait proyek atau notifikasi sistem. Opsional.
A47: 8. | B47: phone | C47: Varchar | D47: 20 | E47: Nomor telepon perusahaan. Dipakai untuk informasi kontak dan validasi data perusahaan. Opsional.
A48: 9. | B48: web | C48: Varchar | D48: 125 | E48: URL website resmi perusahaan. Opsional dan digunakan sebagai informasi tambahan profil perusahaan.
A50: No | B50: Nama Field | C50: Tipe Data | D50: Lebar | E50: Keterangan
A51: 1. | B51: User_Id | C51: bigint | D51: - | E51: Foreign key yang merujuk pada id tabel users. Field ini menunjukkan pengguna yang diberi hak akses terhadap proyek tertentu. Digunakan untuk menentukan role pengguna dalam proyek (Project Manager, Team Member, Client).
A52: 2. | B52: Project_Id | C52: bigint | D52: - | E52: Foreign key yang merujuk pada id tabel projects. Field ini mewakili proyek yang diakses oleh pengguna. Bersama dengan user_id membentuk relasi many-to-many antara pengguna dan proyek.
A55: No | B55: Nama Field | C55: Tipe Data | D55: Lebar | E55: Keterangan
A56: 1. | B56: Id | C56: bigint | D56: - | E56: Primary key sebagai identitas unik setiap proyek dalam sistem.
A57: 2. | B57: client_company_id | C57: bigint | D57: - | E57: Foreign key yang merujuk ke tabel client_companies. Menentukan perusahaan klien yang menjadi pemilik proyek.
A58: 3. | B58: client_user_id | C58: bigint | D58: - | E58: Foreign key yang merujuk ke tabel users. Menunjukkan pengguna klien yang berwenang sebagai penanggung jawab atau perwakilan klien dalam proyek.
A59: 4. | B59: code | C59: Varchar | D59: 20 | E59: Kode unik proyek yang digunakan sebagai identitas administratif dan referensi dokumen.
A60: 5. | B60: name | C60: Varchar | D60: 50 | E60: Nama resmi proyek yang dikelola dalam sistem.
A61: 6. | B61: description | C61: Text | D61: - | E61: Deskripsi proyek secara rinci, mencakup ruang lingkup, tujuan, dan ketentuan pelaksanaan.
A62: 7. | B62: start_date | C62: date | D62: - | E62: Tanggal resmi mulai pelaksanaan proyek berdasarkan perencanaan atau kontrak.
A63: 8. | B63: end_date | C63: date | D63: - | E63: Tanggal rencana penyelesaian proyek. Digunakan untuk evaluasi jadwal dan perhitungan performa waktu.
A64: 9. | B64: direct_cost_plan | C64: decimal | D64: 15.2 | E64: Total rencana biaya langsung (direct cost) yang didefinisikan pada fase perencanaan proyek.
A65: 10. | B65: direct_cost_actual | C65: decimal | D65: 15.2 | E65: Total biaya langsung aktual yang telah dikeluarkan selama pelaksanaan proyek.
A66: 11. | B66: overhead_site_rate | C66: decimal | D66: 5.2 | E66: Persentase biaya overhead lapangan yang ditetapkan untuk proyek.
A67: 12. | B67: overhead_site_cost_plan | C67: decimal | D67: 15.2 | E67: Total rencana biaya overhead lapangan.
A68: 13. | B68: overhead_site_cost_actual | C68: decimal | D68: 15.2 | E68: Total realisasi biaya overhead lapangan.
A69: 14. | B69: administrative_rate | C69: decimal | D69: 5.2 | E69: Persentase biaya administrasi yang dialokasikan untuk proyek.
A70: 15. | B70: administrative_cost_plan | C70: decimal | D70: 15.2 | E70: Total rencana biaya administrasi.
A71: 16. | B71: administrative_cost_actua | C71: decimal | D71: 15.2 | E71: Total biaya administrasi aktual yang telah dikeluarkan.
A72: 17. | B72: contingency_rate | C72: decimal | D72: 5.2 | E72: Persentase dana cadangan (contingency) yang dianggarkan untuk mengantisipasi risiko dalam proyek.
A73: 19. | B73: contingency_cost_actual | C73: decimal | D73: 15.2 | E73: Total penggunaan biaya cadangan aktual.
A74: 20. | B74: profit_rate | C74: decimal | D74: 5.2 | E74: Persentase keuntungan (profit) yang ditargetkan dalam proyek.
A75: 21. | B75: profit_cost_plan | C75: decimal | D75: 15.2 | E75: Total rencana biaya keuntungan proyek.
... A85: 31. | B85: progress_project | C85: decimal | D85: 5.2 | E85: Persentase progres pekerjaan proyek berdasarkan realisasi kegiatan di lapangan. Digunakan untuk evaluasi performa dan perhitungan Earned Value Management (EVM).
A87: No | B87: Nama Field | C87: Tipe Data | D87: Lebar | E87: Keterangan
A88: 1. | B88: Id | C88: bigint | D88: - | E88: Primary key yang menjadi identitas unik setiap kelompok tugas (task group) dalam sistem.
A89: 2. | B89: Project_id | C89: bigint | D89: - | E89: Foreign key yang terhubung ke tabel projects. Field ini menentukan proyek tempat kelompok tugas ini berada, sehingga setiap task group dipetakan secara eksplisit ke satu proyek.
A90: 3. | B90: Name | C90: Varchar | D90: 50 | E90: Nama kelompok tugas yang mendefinisikan kategori atau fase pekerjaan dalam proyek. Digunakan untuk mengorganisasi tugas-tugas secara sistematis.
A91: 4. | B91: Description | C91: text | D91: - | E91: Deskripsi rinci mengenai kelompok tugas, berisi penjelasan ruang lingkup, tujuan, atau ketentuan tambahan terkait kelompok pekerjaan tersebut.
A92: 5. | B92: Order_column | C92: int | D92: - | E92: Angka urutan yang menentukan posisi task group dalam tampilan atau struktur proyek. Nilai ini digunakan untuk menyusun kelompok tugas secara terurut dalam interface maupun logika aplikasi.
A94: No | B94: Nama Field | C94: Tipe Data | D94: Lebar | E94: Keterangan
A95: 1. | B95: id | C95: bigint | D95: - | E95: Primary key sebagai identitas unik setiap tugas yang tercatat dalam sistem.
A96: 2. | B96: project_id | C96: bigint | D96: - | E96: Foreign key yang menghubungkan tugas dengan proyek asalnya. Setiap tugas selalu berada dalam satu proyek tertentu.
A97: 3. | B97: group_id | C97: bigint | D97: - | E97: Foreign key yang merujuk ke tabel task_groups. Field ini menentukan kelompok tugas tempat sebuah task berada dalam struktur proyek.
A98: 4. | B98: Created_by_user_id | C98: bigint | D98: - | E98: Foreign key yang merujuk ke tabel users. Field ini mencatat pengguna yang membuat atau mendaftarkan tugas tersebut ke dalam sistem.
A99: 5. | B99: assigned_to_user_id | C99: bigint | D99: - | E99: Foreign key yang merujuk ke tabel users. Berfungsi untuk menetapkan pengguna yang bertanggung jawab melaksanakan tugas.
A100: 6. | B100: assigned_at | C100: timestamp | D100: - | E100: Waktu penetapan tugas kepada pengguna terkait. Digunakan untuk pelacakan distribusi pekerjaan.
A101: 7. | B101: number | C101: Int | D101: 10 | E101: Nomor urut atau kode identifikasi tugas dalam proyek. Digunakan untuk referensi administratif dan pemetaan internal.
A102: 8. | B102: order_column | C102: int | D102: - | E102: Angka urutan yang menentukan posisi tugas dalam tampilan atau daftar tugas. Memastikan tugas tersusun secara teratur.
A103: 9. | B103: name | C103: varchar | D103: 50 | E103: Nama tugas yang menggambarkan judul atau jenis pekerjaan yang harus diselesaikan.
A104: 10. | B104: description | C104: text | D104: - | E104: Uraian detail mengenai tugas, termasuk ruang lingkup, metode kerja, atau instruksi teknis lainnya.
A105: 11. | B105: start_date | C105: date | D105: - | E105: Tanggal rencana atau aktual dimulainya pengerjaan tugas.
A106: 12. | B106: end_date | C106: date | D106: - | E106: Tanggal rencana atau aktual penyelesaian tugas. Digunakan untuk evaluasi kinerja jadwal.
A107: 13. | B107: budget_task_plan | C107: decimal | D107: 15.2 | E107: Total rencana anggaran yang dialokasikan untuk tugas pada tahap perencanaan proyek.
A108: 14. | B108: budget_task_actual | C108: decimal | D108: 15.2 | E108: Nilai biaya aktual yang telah dikeluarkan untuk menyelesaikan tugas.
A109: 15. | B109: weight_task | C109: decimal | D109: 8.2 | E109: Bobot persentase tugas terhadap keseluruhan proyek. Field ini digunakan dalam perhitungan Earned Value Management (EVM).
A110: 16. | B110: Volume | C110: decimal | D110: 12.2 | E110: Volume pekerjaan yang dialokasikan untuk tugas (misalnya satuan m³, m², unit). Sangat relevan dalam proyek konstruksi berbasis kuantitas.
A111: 17. | B111: unit_cost_task | C111: decimal | D111: 15.2 | E111: Harga satuan pekerjaan untuk tugas, yang digunakan dalam perhitungan total biaya berdasarkan volume.
A112: 18. | B112: progress_task | C112: decimal | D112: 5.2 | E112: Persentase progres penyelesaian tugas berdasarkan laporan aktual pekerjaan di lapangan.
A113: 19. | B113: is_completed | C113: tinyint | D113: 1 | E113: Status penyelesaian tugas. Bernilai 1 jika tugas selesai, dan 0 jika masih dalam proses.
A115: No | B115: Nama Field | C115: Tipe Data | D115: Lebar | E115: Keterangan
A116: 1. | B116: Id | C116: bigint | D116: - | E116: Primary key Digunakan untuk mengidentifikasi setiap alokasi inventaris ke dalam suatu task secara unik. Auto-increment
A117: 2. | B117: Inventory_id | C117: bigint | D117: - | E117: Foreign key yang merujuk ke tabel inventories. Menunjukkan item inventaris mana yang dialokasikan.
A118: 3. | B118: Task_id | C118: Bigint | D118: - | E118: Foreign key yang merujuk ke tabel tasks. Menunjukkan alokasi inventaris dipakai untuk task yang mana.
A119: 4. | B119: Allocated_by_user_id | C119: Bigint | D119: - | E119: Foreign key yang merujuk ke tabel users. Mengidentifikasi user yang melakukan proses alokasi inventaris.
A120: 5. | B120: Quantity_allocated | C120: Decimal | D120: 15.2 | E120: jumlah inventaris yang dialokasikan untuk task tertentu.
A121: 6. | B121: Cost_at_allocation | C121: Decimal | D121: 15.2 | E121: Harga satuan inventaris pada saat dialokasikan ke task.
A122: 7. | B122: Notes | C122: Text | D122: - | E122: Catatan tambahan terkait alokasi inventaris.
...

Sheet Sheet5
A1: Keterangan
A2: Aktor | B2: : | C2: Project Manager.
A3: Tujuan | B3: : | C3: Mengelola data proyek seperti penambahan, pembaruan, dan penghapusan.
A4: Hasil | B4: : | C4: Data proyek diperbarui di database dan tampil di halaman proyek.

Sheet Sheet6
A1: No | B1: Method | C1: Endpoint | D1: Description | E1: Request Body | F1: Response
A2: 1. | B2: GET | C2: /login | D2: Menampilkan formulir masuk | E2: N/A | F2: Tampilan formulir login HTML
A3: 2. | B3: POST | C3: /login | D3: Mencoba autentikasi pengguna | E3: email (string), password (string), _token (CSRF token) | F3: Dialihkan ke dasbor jika berhasil, kembali ke login dengan kesalahan jika gagal
A4: 3. | B4: POST | C4: /logout | D4: Keluar dari pengguna yang diautentikasi | E4: N/A (requires auth session) | F4: Dialihkan ke beranda
A5: 4. | B5: GET | C5: /password/forgot | D5: Menampilkan formulir lupa kata sandi | E5: N/A | F5: Tampilan formulir lupa kata sandi HTML
A6: 5. | B6: POST | C6: /password/forgot | D6: Mengirim tautan pengaturan ulang kata sandi | E6: email (string), password (string), _token (CSRF token) | F6: Pesan berhasil atau kesalahan
A7: 6. | B7: GET | C7: /password/new/{token} | D7: Menampilkan formulir kata sandi baru | E7: N/A | F7: Formulir kata sandi baru HTML
A8: 7. | B8: POST | C8: /password/new | D8: Menyimpan kata sandi baru | E8: email (string), password (string), _token (CSRF token) | F8: Dialihkan ke login jika berhasil
B12: Method | C12: Endpoint | D12: Deskripsi | E12: Request | F12: Response
B13: GET | C13: /labels | D13: Mengambil semua data label (termasuk pagination jika ada). | E13: – | F13: { data: [...], meta: {...} }
B14: GET | C14: /labels/create | D14: Mengambil data pendukung untuk form create (opsional, biasanya tidak dipakai API). | E14: – | F14: { form_options: {...} }
B15: POST | C15: /labels | D15: Membuat label baru. | E15: { name: string, color: string } | F15: { message: "Label created", data: {...} }
B16: GET | C16: /labels/{label}/edit | D16: Mengambil data label utk ditampilkan di form edit. | E16: – | F16: { data: {...} }
B17: PUT/PATCH | C17: /labels/{label} | D17: Mengupdate label. | E17: { name: string, color: string } | F17: { message: "Label updated", data: {...} }
B18: DELETE | C18: /labels/{label} | D18: Soft delete label (bergantung model menggunakan SoftDeletes). | E18: – | F18: { message: "Label deleted" }
B19: DELETE | C19: /labels/{label}/force-delete | D19: Menghapus permanen label dari database. | E19: – | F19: { message: "Label permanently deleted" }
B20: POST | C20: /labels/{labelId}/restore | D20: Restore label yang telah di-soft-delete. | E20: – | F20: { message: "Label restored", data: {...} }
B23: Method | C23: Endpoint | D23: Deskripsi | E23: Request Body | F23: Response
B24: POST | C24: /{project}/tasks/{task}/attachments/upload | D24: Mengunggah attachment untuk task tertentu pada project. | E24: FormData:• file: file upload | F24: { message: "Attachment uploaded", data: {...} }
B25: DELETE | C25: /{project}/tasks/{task}/attachments/{attachment} | D25: Menghapus attachment milik task tertentu. | E25: – | F25: { message: "Attachment deleted" }
... B42: POST | C42: /evm-records/recalculate | D42: Melakukan proses rekalkulasi EVM (Earned Value Management) secara keseluruhan untuk project. | E42: { project_id: number } | F42: Status sukses + hasil recalculation (CPI, SPI, PV, EV, AC, dsb)

Sheet Sheet2
A1: NO | B1: SPRINT | C1: ACTIVITY | D1: START DATE | E1: END DATE | F1: DURATION (days) | G1: WEIGHT (%) | H1: STATUS
A2: 1 | B2: Sprint 0 | C2: Identifikasi Kebutuhan Sistem (Wawancara, Observasi, Analisis Masalah) | D2: 45236 | E2: 45240 | F2: 5 | G2: 0.02 | H2: To do
A3: 2 | B3: Sprint 0 | C3: Mencari Studi Pustaka sebagai referensi | D3: 45243 | E3: 45406 | F3: 164 | G3: 0.55 | H3: To do
A4: 3 | B4: Sprint 0 | C4: Perancangan Alur Sistem (Flowchart, UML) | D4: 45407 | E4: 45441 | F4: 35 | G4: 0.12 | H4: To do
A5: 4 | B5: Sprint 0 | C5: Perancangan Database (Normalisasi, ERD, LRS, Spesifikasi Database) | D5: 45442 | E5: 45485 | F5: 44 | G5: 0.15 | H5: To do
A6: 5 | B6: Sprint 0 | C6: Perancangan UI | D6: 45488 | E6: 45527 | F6: 40 | G6: 0.14 | H6: To do
A7: 6 | B7: Sprint 0 | C7: Perancangan Product Backlog | D7: 45530 | E7: 45537 | F7: 8 | G7: 0.03 | H7: To do
B8: TOTAL DURATION SPRINT-0 | D8: 45236 | E8: 45537 | F8: 296 | G8: 0.4235
B9: CONTRIBUTE SPRINT-0
A10: 1 | B10: Sprint 1 | C10: Pembuatan Database, Tabel Akses, User, dan Level | D10: 45538 | E10: 45538 | F10: 1 | G10: 0.03 | H10: To do
A11: 2 | B11: Sprint 1 | C11: Pembuatan UI Login | D11: 45539 | E11: 45545 | F11: 7 | G11: 0.23 | H11: To do
A12: 3 | B12: Sprint 1 | C12: Implementasi autentikasi | D12: 45546 | E12: 45553 | F12: 8 | G12: 0.26 | H12: To do
A13: 4 | B13: Sprint 1 | C13: Pembuatan Menu logout | D13: 45554 | E13: 45554 | F13: 1 | G13: 0.03 | H13: To do
A14: 5 | B14: Sprint 1 | C14: Pembuatan tampilan dashboard | D14: 45555 | E14: 45561 | F14: 7 | G14: 0.23 | H14: To do
A15: 6 | B15: Sprint 1 | C15: Blackbox Testing Sprint 1 | D15: 45562 | E15: 45565 | F15: 4 | G15: 0.13 | H15: To do
A16: 7 | B16: Sprint 1 | C16: UAT, Review & Retrospective | D16: 45566 | E16: 45568 | F16: 3 | G16: 0.1 | H16: To do
C17: TOTAL DURATION SPRINT-1 | D17: 45538 | E17: 45568 | F17: 31 | G17: 0.0443
C18: CONTRIBUTE SPRINT-1
A19: 1 | B19: Sprint 2 | C19: Pembuatan Tabel Database Client | D19: 45568 | E19: 45568 | F19: 1 | G19: 0.03 | H19: To do
A20: 2 | B20: Sprint 2 | C20: Pembuatan UI Halaman Customer | D20: 45569 | E20: 45575 | F20: 7 | G20: 0.24 | H20: To do
A21: 3 | B21: Sprint 2 | C21: Implementasi Backend (CRUD) Modul Client | D21: 45576 | E21: 45582 | F21: 7 | G21: 0.24 | H21: To do
A22: 4 | B22: Sprint 2 | C22: Pembuatan UI Halaman User | D22: 45583 | E22: 45589 | F22: 7 | G22: 0.24 | H22: To do
A23: 5 | B23: Sprint 2 | C23: Implementasi Backend (CRUD) Modul User | D23: 45590 | E23: 45596 | F23: 7 | G23: 0.24 | H23: To do
C24: TOTAL DURATION SPRINT-2 | D24: 45568 | E24: 45596 | F24: 29 | G24: 0.0415
C25: CONTRIBUTE SPRINT-2
A26: 1 | B26: Sprint 3 | C26: Pembuatan Tabel Database Project | D26: 45597 | E26: 45597 | F26: 1 | G26: 0.02 | H26: To do
A27: 2 | B27: Sprint 3 | C27: Pembuatan UI Halaman Project | D27: 45600 | E27: 45604 | F27: 5 | G27: 0.12 | H27: To do
A28: 3 | B28: Sprint 3 | C28: Implementasi Backend (CRUD) Modul Project | D28: 45607 | E28: 45611 | F28: 5 | G28: 0.12 | H28: To do
A29: 4 | B29: Sprint 3 | C29: Pembuatan UI Task dan sub Task | D29: 45614 | E29: 45618 | F29: 5 | G29: 0.12 | H29: To do
A30: 5 | B30: Sprint 3 | C30: Implementasi Backend (CRUD) Modul Task | D30: 45621 | E30: 45625 | F30: 5 | G30: 0.12 | H30: To do
A31: 6 | B31: Sprint 3 | C31: Pembuatan UI Halaman Inventories | D31: 45628 | E31: 45629 | F31: 2 | G31: 0.05 | H31: To do
A32: 7 | B32: Sprint 3 | C32: Implementasi Backend (CRUD) Modul Inventories | D32: 45630 | E32: 45632 | F32: 3 | G32: 0.07 | H32: To do
A33: 8 | B33: Sprint 3 | C33: Pembuatan UI Halaman Work Report | D33: 45635 | E33: 45636 | F33: 2 | G33: 0.05 | H33: To do
A34: 9 | B34: Sprint 3 | C34: Implementasi Backend (CRUD) Modul Work Report | D34: 45637 | E34: 45639 | F34: 3 | G34: 0.07 | H34: To do
A35: 10 | B35: Sprint 3 | C35: Blackbox Testing Sprint 3 | D35: 45628 | E35: 45632 | F35: 5 | G35: 0.12 | H35: To do
A36: 11 | B36: Sprint 3 | C36: UAT, Review & Retrospective | D36: 45635 | E36: 45639 | F36: 5 | G36: 0.12 | H36: To do
C37: TOTAL DURATION SPRINT-3 | D37: 45597 | E37: 45639 | F37: 41 | G37: 0.0587
C38: CONTRIBUTE SPRINT-3
A39: 1 | B39: Sprint 4 | C39: Pembuatan Tabel Database EVM (PV, EV, AC) | D39: 45642 | E39: 45646 | F39: 5 | G39: 0.14 | H39: To do
A40: 2 | B40: Sprint 4 | C40: Implementasi Perhitungan PV (Planned Value) | D40: 45649 | E40: 45653 | F40: 5 | G40: 0.14 | H40: To do
A41: 3 | B41: Sprint 4 | C41: Implementasi Perhitungan EV (Earned Value) | D41: 45656 | E41: 45660 | F41: 5 | G41: 0.14 | H41: To do
A42: 4 | B42: Sprint 4 | C42: Implementasi Perhitungan AC (Actual Cost) | D42: 45663 | E42: 45667 | F42: 5 | G42: 0.14 | H42: To do
A43: 5 | B43: Sprint 4 | C43: Implementasi Perhitungan SV, CV, SPI, CPI | D43: 45670 | E43: 45674 | F43: 5 | G43: 0.14 | H43: To do
A44: 6 | B44: Sprint 4 | C44: Pembuatan UI Dashboard EVM | D44: 45677 | E44: 45681 | F44: 5 | G44: 0.14 | H44: To do
A45: 7 | B45: Sprint 4 | C45: Blackbox Testing Sprint 4 | D45: 45684 | E45: 45688 | F45: 5 | G45: 0.14 | H45: To do
C46: TOTAL DURATION SPRINT-4 | D46: 45642 | E46: 45688 | F46: 35 | G46: 0.0501
C47: CONTRIBUTE SPRINT-4
A48: 1 | B48: Sprint 5 | C48: Implementasi Real-time Update Progress | D48: 45691 | E48: 45695 | F48: 5 | G48: 0.25 | H48: To do
A49: 2 | B49: Sprint 5 | C49: Pembuatan Grafik Kurva S | D49: 45698 | E49: 45702 | F49: 5 | G49: 0.25 | H49: To do
A50: 3 | B50: Sprint 5 | C50: Implementasi Alert & Notifikasi | D50: 45705 | E50: 45709 | F50: 5 | G50: 0.25 | H50: To do
A51: 5 | B51: Sprint 5 | C51: Blackbox Testing Sprint 5 | D51: 45719 | E51: 45723 | F51: 5 | G51: 0.25 | H51: To do
C52: TOTAL DURATION SPRINT-5 | D52: 45691 | E52: 45723 | F52: 20 | G52: 0.0286
C53: CONTRIBUTE SPRINT-5
A54: 1 | B54: Sprint 6 | C54: Integration Testing Seluruh Modul | D54: 45726 | E54: 45730 | F54: 5 | G54: 0.02 | H54: To do
A55: 2 | B55: Sprint 6 | C55: User Acceptance Testing (UAT) Lengkap | D55: 45733 | E55: 45737 | F55: 5 | G55: 0.02 | H55: To do
A56: 3 | B56: Sprint 6 | C56: Perbaikan Bug & Enhancement | D56: 45740 | E56: 45744 | F56: 5 | G56: 0.02 | H56: To do
A57: 4 | B57: Sprint 6 | C57: Deployment ke Server Production | D57: 45747 | E57: 45751 | F57: 5 | G57: 0.02 | H57: To do
A58: 5 | B58: Sprint 6 | C58: Dokumentasi Sistem & User Manual | D58: 45754 | E58: 45980 | F58: 227 | G58: 0.92 | H58: To do
C59: TOTAL DURATION SPRINT-6 | D59: 45726 | E59: 45980 | F59: 247 | G59: 0.3534
C60: CONTRIBUTE SPRINT-6
D62: TOTAL DURATION SPRINT 0-6 | F62: 699
D63: TOTAL WEIGHT SPRINT 0-6 | G63: 1
D64: MONTH(30 days) | F64: 23.3

Sheet Sheet4
A1: No | B1: Nama tabel | C1: Jumlah Field | D1: keterangan
A2: 1. | B2: Client_companies | C2: 13 | D2: Menyimpan data perusahaan klient
A3: 2. | B3: owner_companies | C3: 13 | D3: Menyimpan data perusahaaan pemilik proyek
A4: 3. | B4: Users | C4: 15 | D4: menyimpan data user
A7: Method | B7: Endpoint | C7: Deskripsi | D7: Request | E7: Body | F7: Response
A8: GET | B8: /clients/companies | C8: Mendapatkan list client companies | D8: Query: ?search=, ?status=, ?with_trashed= | E8: - | F8: {data: [...], pagination: {...}}
A9: POST | B9: /clients/companies | C9: Membuat client company baru | D9: Headers: Authorization: Bearer {token} | E9: {name, address, phone, email, website} | F9: {message, data: {...}}
A10: PUT | B10: /clients/companies/{companyId} | C10: Update client company | D10: Headers: Authorization: Bearer {token} | E10: {name, address, phone, email, website} | F10: {message, data: {...}}
A11: DELETE | B11: /clients/companies/{companyId} | C11: Soft delete client company | D11: Headers: Authorization: Bearer {token} | E11: - | F11: {message}
A12: DELETE | B12: /clients/companies/{companyId}/force-delete | C12: Permanent delete client company | D12: Headers: Authorization: Bearer {token} | E12: - | F12: {message}
A13: POST | B13: /clients/companies/{companyId}/restore | C13: Restore deleted client company | D13: Headers: Authorization: Bearer {token} | E13: - | F13: {message, data: {...}}
A15: Method | B15: Endpoint | C15: Deskripsi | D15: Request | E15: Body | F15: Response
A16: GET | B16: /clients/users | C16: Get list client users | D16: Query: ?search=, ?company_id=, ?with_trashed= | E16: - | F16: {data: [...], pagination: {...}}
A17: POST | B17: /clients/users | C17: Create new client user | D17: Headers: Authorization: Bearer {token} | E17: {name, email, password, client_company_id, phone} | F17: {message, data: {...}}
A18: PUT | B18: /clients/users/{userId} | C18: Update client user | D18: Headers: Authorization: Bearer {token} | E18: {name, email, password?, client_company_id, phone} | F18: {message, data: {...}}
A19: DELETE | B19: /clients/users/{userId} | C19: Soft delete client user | D19: Headers: Authorization: Bearer {token} | E19: - | F19: {message}
... A85: POST | B85: /{project}/tasks/{task}/comment | C85: Menambahkan komentar baru pada task tertentu | D85: Path params: {project}, {task} | E85: json { "comment": "string" } | F85: Data komentar yang berhasil disimpan (JSON)

Sheet Sheet7
A1: No | B1: Kriteria Penerimaan | C1: Tester | D1: Hasil | E1: Rating (1–5) | F1: Catatan
A2: 1. | B2: User dapat melakukan aktivasi akun | C2: Stakeholder C | D2: ✅ Accepted | E2: 4 | F2: Aktivasi berhasil, disarankan notifikasi lebih jelas
A3: 2. | B3: Admin dapat mengelola client companies dengan mudah | C3: Stakeholder A | D3: ✅ Accepted | E3: 5 | F3: Antarmuka intuitif; soft delete sangat berguna
A4: 3. | B4: Admin dapat mengelola owner companies | C4: Stakeholder B | D4: ✅ Accepted | E4: 5 | F4: Fitur lengkap dan stabil
A5: 4. | B5: User dapat mengubah profil sendiri | C5: Stakeholder C | D5: ✅ Accepted | E5: 4 | F5: Disarankan preview foto yang lebih besar
A6: 5. | B6: Fitur filter berfungsi dengan cepat | C6: Stakeholder A | D6: ✅ Accepted | E6: 5 | F6: Response time < 1 detik
A7: 6. | B7: Upload foto profil berfungsi dengan baik | C7: Stakeholder C | D7: ✅ Accepted | E7: 4 | F7: Tambahkan fitur crop foto
A8: 7. | B8: Soft delete, archive, dan restore berfungsi dengan baik | C8: Stakeholder A | D8: ✅ Accepted | E8: 5 | F8: Data yang dihapus masuk ke archive list dan dapat dipulihkan. Sangat membantu keamanan data
A9: 8. | B9: Force delete dengan authorization | C9: Stakeholder B | D9: ✅ Accepted | E9: 5 | F9: Mekanisme keamanan kuat, hanya admin yang diizinkan
A12: No | B12: Kriteria Penerimaan | C12: Tester | D12: Hasil | E12: Rating (1–5) | F12: Catatan
A13: 1. | B13: User dapat login dengan lancar | C13: Stakeholder A | D13: ✅ Accepted | E13: 5 | F13: UI user-friendly dan proses login cepat
A14: 2. | B14: Sistem dapat membedakan akses per role (RBAC) | C14: Stakeholder B | D14: ✅ Accepted | E14: 5 | F14: RBAC berjalan baik dan konsisten
A15: 3. | B15: Dashboard menampilkan informasi yang relevan | C15: Stakeholder A | D15: ✅ Accepted | E15: 4 | F15: –
A16: 4. | B16: Admin dapat mengelola user dengan mudah | C16: Stakeholder B | D16: ✅ Accepted | E16: 4 | F16: Perlu fitur export user list (backlog Sprint 6)
A17: 5. | B17: Logout berfungsi dengan aman | C17: Stakeholder A | D17: ✅ Accepted | E17: 5 | F17: –
A18: 6. | B18: Admin dapat menambah user baru | C18: Stakeholder B | D18: ✅ Accepted | E18: 5 | F18: Form input jelas; validasi berjalan baik
A19: 7. | B19: Admin dapat mengedit data user | C19: Stakeholder A | D19: ✅ Accepted | E19: 4 | F19: Perlu auto-preview foto profil
A20: 8. | B20: Admin dapat melakukan soft delete, archive dan restore user | C20: Stakeholder B | D20: ✅ Accepted | E20: 5 | F20: Data terarsip dengan baik; restore berfungsi
A21: 9. | B21: Force delete hanya untuk Admin | C21: Stakeholder B | D21: ✅ Accepted | E21: 5 | F21: Mekanisme authorization aman
A23: No | B23: Feedback | C23: Keterangan | D23: Status
A24: 1. | B24: Aktivasi akun sudah berjalan baik | C24: Stakeholder puas, alur jelas dan mudah dipahami | D24: ✅ Accepted
A25: 2. | B25: Fitur Archive/Restore sangat membantu | C25: Dinyatakan efektif untuk kebutuhan administrasi | D25: ✅ Accepted
A26: 3. | B26: Informasi Last Login dianggap menarik untuk wacana pengembangan | C26: Ditandai sebagai insight jangka panjang, bukan prioritas sprint | D26: 🔍 Catatan Umum
A27: 4. | B27: Mass import user (Excel) dianggap akan bermanfaat suatu hari nanti | C27: Dicatat sebagai opsi pengembangan di masa mendatang, tidak mempengaruhi scope | D27: 🔍 Catatan Umum
A28: 5. | B28: UI filter user cukup baik namun bisa dipoles lagi | C28: Masuk sebagai catatan UI/UX umum, bukan pekerjaan sprint | D28: 🔍 Catatan Umum
A30: Jenis Testing | B30: Total Test Case | C30: Passed | D30: Failed | E30: Pass Rate
A31: Blackbox Testing | B31: 18 | C31: 18 | D31: 0 | E31: 1
A32: User Acceptance Testing (UAT) | B32: 7 | C32: 7 | D32: 0 | E32: 1
A35: No | B35: Kriteria DoD | C35: Status | H35: No | I35: Kriteria DoD | J35: Status
A36: 1. | B36: User baru menerima email aktivasi | C36: Done | H36: 1. | I36: Semua fitur inti (Project, Task, Subtask, Dependencies, Inventory, Work Report) berjalan sesuai kebutuhan tanpa error mayor. | J36: Done
A37: 2. | B37: Token aktivasi berlaku 24 jam dan aman | C37: ✅ Done | H37: 2. | I37: Perhitungan EVM (PV, EV, AC, SPI, CPI) otomatis dan akurat berdasarkan progres dan laporan pekerjaan. | J37: Done
A38: 3. | B38: User tidak bisa login sebelum aktivasi | C38: ✅ Done | H38: 3. | I38: Integrasi antar modul (Task → Subtask → Progress → EVM → Dashboard) berjalan sinkron tanpa inkonsistensi data. | J38: Done
A39: 4. | B39: Manajemen user (update/reset) berjalan baik | C39: ✅ Done | H39: 4. | I39: Validasi input tersedia pada setiap form (prevent over-allocation, circular dependency, data invalid). | J39: Done
A40: 5. | B40: Soft delete → Archive → Restore berfungsi | C40: ✅ Done | H40: 5. | I40: Tampilan fitur dapat digunakan tanpa hambatan pada perangkat desktop. | J40: Done
A41: 6. | B41: Seluruh fitur lulus UAT | C41: ✅ Done | H41: 6. | I41: Dokumentasi API dan alur penggunaan fitur tersedia dan dapat diakses oleh stakeholder. | J41: Done
A42: 7. | B42: Patch bug prioritas diimplementasi | C42: ✅ Done | H42: 7. | I42: Sistem telah melalui pengujian Unit Test dan Blackbox Test dengan hasil sesuai ekspektasi. | J42: Done
A43: 8. | B43: Dokumentasi API diperbarui | C43: ✅ Done | H43: 8. | I43: UAT disetujui oleh stakeholder tanpa permintaan perubahan kritikal. | J43: Done
A44: 9. | B44: Code ter-push dan ter-review | C44: ✅ Done | H44: 9. | I44: Deployment ke environment staging berhasil tanpa error blocker. | J44: Done
A45: 10. | B45: Deploy ke environment testing | C45: ✅ Done | H45: 10. | I45: Semua backlog minor dicatat untuk rencana sprint berikutnya. | J45: Done
A49: No | B49: Aspek Evaluasi | C49: Ulasan
A50: 1. | B50: Apa yang berjalan dengan baik? | C50: a) Proses email aktivasi stabil dan berjalan sesuai skenario
C51: b) Fitur Archive/Restore sangat membantu adminsitrasi user
C52: c) Blackbox testing dapat berjalan lebih cepat karena modul modular
C53: d) Dokumentasi API lebih terstruktur dibanding Sprint 1
C54: e) Tidak ada blocker besar sepanjang sprint
A55: 2. | B55: Apa yang dapat diperbaiki? | C55: a) Estimasi fitur Archive lebih besar dari perkiraan (overrun 0.5 hari)
C56: b) UI filter user masih kurang intuitif bagi user non-teknis
C57: c) Alur reset password perlu penjelasan tambahan di dokumentasi
C58: d) Error handling email (SMTP delay) belum tertangani optimal
C59: e) Perlu konsistensi penamaan status user (active, inactive, archived)
A60: 3. | B60: Tantangan yang dihadapi | C60: a) Sinkronisasi status user (email activation vs DB) memerlukan revisi struktur service
C61: b) SMTP provider mengalami delay sehingga perlu retry mechanism
C62: c) Perbedaan kebutuhan stakeholder terkait status Archived vs Inactive
A63: 4. | B63: Pembelajaran yang didapat | C63: a) Fitur yang melibatkan email perlu buffer waktu testing lebih besar
C64: b) Penambahan Activity Log sangat mempermudah debugging user management
C65: c) Soft delete lebih aman dibanding hard delete dalam konteks audit
C66: d) Penulisan dokumentasi API paralel dengan coding mengurangi rework
C67: e) Testing parallel dengan development lebih efisien dibanding testing di akhir sprint
A68: 5. | B68: Feedback dari stakeholder | C68: a)Stakeholder memberikan rating kepuasan Sprint 2 sebesar 4.6/5, menilai seluruh deliverable sesuai ekspektasi.
C69: b) Usulan penambahan kolom Last Login dicatat sebagai masukan keamanan jangka panjang, namun tidak dimasukkan ke backlog sprint agar fokus pengembangan tetap terjaga.
C70: c) Fitur mass import user (Excel) dinilai potensial untuk efisiensi di masa mendatang, tetapi ditandai sebagai wacana pengembangan, bukan prioritas sprint maupun backlog aktif.

Sheet Sheet8
A1: No | B1: Fitur | C1: User Story | D1: Estimasi | E1: Weight(%) | H1: Kategori | I1: Kriteria DoD | K1: Kategori | L1: Kriteria DoD
A2: 1. | B2: Perhitungan PV, EV, AC | C2: Sebagai Project Manager, saya ingin sistem dapat menghitung Planned Value (PV), Earned Value (EV), dan Actual Cost (AC), sehingga saya dapat mengetahui performa progres proyek secara numerik. | D2: 12 hari | E2: 0.2 | H2: Fungsionalitas | I2: a) Logika perhitungan EVM (PV, EV, AC, CPI, SPI, CV, SV) berjalan tanpa error. b) Data dapat diambil dari database dan diproses secara otomatis. c) Dashboard mampu menampilkan nilai EVM secara real-time. | K2: Fungsionalitas | L2: a) CRUD Project berfungsi penuh, termasuk assignment client dan owner company. b) CRUD Task berjalan lengkap dengan fitur progress tracking. c) CRUD Subtask bekerja dan terhubung dengan parent task. d) Task Dependencies dapat diatur (Finish-to-Start, Start-to-Start, dsb.).
A3: 2. | B3: Perhitungan CPI, SPI, CV, SV | C3: Sebagai Project Manager, saya ingin sistem dapat menghitung Cost Performance Index (CPI), Schedule Performance Index (SPI), Cost Variance (CV), dan Schedule Variance (SV) secara otomatis berdasarkan nilai EVM. | D3: 7 hari | E3: 0.2 | H3: Validasi & Akurasi | I3: a) Hasil perhitungan diverifikasi menggunakan sampel studi kasus. b) Toleransi maksimal kesalahan perhitungan ≤ 1%. | K3: Teknis / Backend | L3: a) API backend lengkap dan terdokumentasi untuk seluruh modul (Project, Task, Subtask, Dependencies).
A4: 3. | B4: Dashboard Monitoring EVM | C4: Sebagai pengguna, saya ingin melihat hasil perhitungan EVM melalui tampilan dashboard agar dapat memantau status proyek secara cepat dan mudah dipahami. | D4: 7 hari | E4: 0.2 | H4: UI & UX | I4: a) Dashboard responsif pada perangkat desktop dan tablet. b) Indikator performa menggunakan skema warna yang mudah dipahami (Hijau/Kuning/Merah). | K4: Kualitas dan Pengujian | L4: a) Semua fitur lulus pengujian blackbox testing tanpa error mayor.
A5: 4. | B5: Discussion task | C5: Sebagai pengguna, saya ingin dapat memberikan komentar, catatan, atau diskusi pada setiap task agar kolaborasi tim berjalan lebih efektif dan riwayat pembahasan dapat terdokumentasi. | D5: 7 hari | E5: 0.2
A6: 5. | B6: Testing dan UAT | C6: Memastikan semua fitur berfungsi dengan baik | D6: 7 hari | E6: 0.2 | H6: Integrasi | I6: a) Data progress proyek terhubung dengan modul Task dan Cost. b) Seluruh nilai berhasil tersimpan secara otomatis ke tabel evm_records. | K6: Validasi Pengguna | L6: a) User Acceptance Test (UAT) telah dilakukan dan disetujui oleh stakeholder.
C7: Total | D7: 35 hari | E7: 1 | H7: Testing | I7: a) Unit test minimal mencapai 80% coverage pada modul kalkulasi EVM. b) Blackbox testing selesai dan diterima tanpa error kritikal.
H8: Dokumentasi | I8: a) Dokumentasi API endpoint telah tersedia dan dapat diakses tim. b) SOP pengisian progress EVM dicantumkan dalam wiki sistem.
H9: Deployment | I9: a) Fitur berhasil di-deploy pada staging environment. b) Tidak terdapat bug blocker atau error yang menghentikan fungsi sistem.

Sheet Sheet9
A1: No | B1: Fitur | C1: Test Case | D1: Input | E1: Expected Output | F1: Actual Output | G1: Status | I1: No | J1: Kriteria Penerimaan | K1: Tester | L1: Hasil | M1: Rating (1–5) | N1: Catatan | P1: No | Q1: Feedback | R1: Prioritas | S1: Action | U1: No | V1: Feedback | W1: Prioritas | X1: Action
A2: 1. | B2: Project | C2: Create project | D2: Data valid | E2: Project tersimpan | F2: Sesuai expected | G2: Pass | I2: 1. | J2: PM dapat membuat dan mengelola proyek | K2: Stakeholder A | L2: Accepted | M2: 5 | N2: Fitur lengkap dan intuitif | P2: 1. | Q2: Modul Project dinilai sudah stabil dan mudah digunakan. Alur pembuatan, pembaruan, dan pengelolaan proyek berjalan konsisten tanpa kendala berarti. | R2: - | S2: Accepted | U2: 1. | V2: Aktivasi akun sudah berjalan baik | W2: - | X2: Accepted
A3: 2. | B3: Project | C3: Edit project | D3: Data baru | E3: Project terupdate | F3: Sesuai expected | G3: Pass | I3: 2. | J3: Task management mudah digunakan | K3: Stakeholder B | L3: Accepted | M3: 5 | N3: Tampilan timeline mempermudah pemantauan progres | P3: 2. | Q3: Pengelolaan Task berjalan baik dan fungsional. User merasa proses penugasan dan pelacakan progres cukup jelas dan mendukung workflow tim. | R3: - | S3: Accepted | U3: 2. | V3: Fitur Archive/Restore sangat membantu | W3: - | X3: Accepted
A4: 3. | B4: Project | C4: Delete project | D4: Klik delete | E4: Project terhapus | F4: Sesuai expected | G4: Pass | I4: 3. | J4: Subtask breakdown memudahkan planning | K4: Stakeholder A | L4: Accepted | M4: 5 | N4: Fitur hierarki sangat membantu | P4: 3. | Q4: Fitur Task Dependencies memberikan nilai tambah signifikan bagi perencanaan dan kontrol timeline. Visualisasi hubungan antar task membantu user memahami urutan pekerjaan dengan lebih baik. | R4: - | S4: Accepted | U4: 3. | V4: Informasi Last Login dianggap menarik untuk wacana pengembangan | W4: Low | X4: Catatan Umum
A5: 4. | B5: Project | C5: Calculate statistics | D5: - | E5: EVM metrics benar | F5: Sesuai expected | G5: Pass | I5: 4. | J5: Task dependencies berfungsi dengan baik | K5: Stakeholder B | L5: Accepted | M5: 4 | N5: Perlu dokumentasi penggunaan hubungan antar task | P5: 4. | Q5: Modul Inventories dianggap bermanfaat untuk dokumentasi aset, dan pengguna merasa struktur datanya sudah cukup relevan dengan kebutuhan proyek. | R5: - | S5: Accepted | U5: 4. | V5: Mass import user (Excel) dianggap akan bermanfaat suatu hari nanti | W5: Low | X5: Catatan Umum
A6: 5. | B6: Task | C6: Create task | D6: Data valid | E6: Task tersimpan | F6: Sesuai expected | G6: Pass | I6: 5. | J6: Inventory management terintegrasi | K6: Stakeholder A | L6: Accepted | M6: 5 | N6: Kontrol material menjadi lebih presisi | P6: 5. | Q6: Mekanisme Inventory Allocation ke task memberikan kontrol yang lebih detail terhadap penggunaan material di lapangan. Stakeholder menilai fitur ini mendukung transparansi budget dan resource tracking. | R6: - | S6: Accepted | U6: 5. | V6: UI filter user cukup baik namun bisa dipoles lagi | W6: Medium | X6: Catatan Umum
A7: 6. | B7: Task | C7: Update progress | D7: Progress: 50% | E7: EV terhitung otomatis | F7: Sesuai expected | G7: Pass | I7: 6. | J7: Engineer dapat input work report dengan bukti foto | K7: Stakeholder C | L7: Accepted | M7: 5 | N7: Lampiran foto membantu verifikasi lapangan | P7: 6. | Q7: Fitur Work Report dengan dokumentasi foto memberikan kejelasan progres aktual di lapangan dan sangat membantu proses audit internal maupun evaluasi timeline. | R7: - | S7: Accepted
A8: 7. | B8: Task | C8: Assign to engineer | D8: Select user | E8: Task assigned ke user | F8: Sesuai expected | G8: Pass | I8: 7. | J8: Progress tracking akurat dan sinkron dengan perhitungan EVM | K8: Stakeholder B | L8: Accepted | M8: 5 | N8: Perhitungan EV, SPI, dan CPI sesuai ekspektasi | P8: 7. | Q8: Fitur Discussion Team dalam task dinilai berguna, namun pengguna berharap adanya peningkatan agar komunikasi terasa lebih real-time dan terpusat. | R8: Medium | S8: Masuk backlog Sprint 4
A9: 8. | B9: Subtask | C9: Create subtask | D9: Data valid | E9: Subtask tersimpan | F9: Sesuai expected | G9: Pass | P9: 8. | Q9: Sistem notifikasi diusulkan untuk ditingkatkan, terutama untuk pengingat deadline task dan perubahan status penting agar pengguna tidak bergantung pada pengecekan manual. | R9: Low | S9: Catatan Umum
A10: 9. | B10: Subtask | C10: Update progress | D10: Progress: 75% | E10: Progress parent task ikut diperbarui | F10: Sesuai expected | G10: Pass
A11: 10. | B11: Dependencies | C11: Create FS dependency | D11: Task A → Task B | E11: Dependency berhasil dibuat | F11: Sesuai expected | G11: Pass
A12: 11. | B12: Dependencies | C12: Prevent circular dependency | D12: Task A ↔ Task B | E12: Sistem menolak relasi melingkar | F12: Sesuai expected | G12: Pass
A13: 12. | B13: Dependencies | C13: Auto recalc schedule | D13: Update durasi Task A | E13: Task B otomatis menyesuaikan jadwal | F13: Sesuai expected | G13: Pass
A14: 13. | B14: Inventory | C14: Add inventory | D14: Data valid | E14: Inventory tersimpan | F14: Sesuai expected | G14: Pass
A15: 14. | B15: Inventory | C15: Allocate inventory | D15: Quantity: 10 | E15: Allocation sukses | F15: Sesuai expected | G15: Pass
A16: 15. | B16: Inventory | C16: Prevent over-allocation | D16: Qty > stock | E16: Error message muncul | F16: Sesuai expected | G16: Pass
A17: 16. | B17: Work Report | C17: Submit work report | D17: Data + Foto | E17: Report tersimpan | F17: Sesuai expected | G17: Pass
A18: 17. | B18: Work Report | C18: Auto update progress | D18: Laporan: 80% | E18: Task progress berubah menjadi 80% | F18: Sesuai expected | G18: Pass

Sheet Sheet11
A1: Fitur Utama | B1: Sub-Fitur | C1: Deskripsi
A2: Project | B2: CRUD Project | C2: Sistem mendukung pembuatan, pembaruan, penghapusan, dan pengelolaan data proyek.
B3: Calculate Statistics | C3: Sistem menghitung indikator proyek seperti PV, EV, AC, SPI, dan CPI secara otomatis berdasarkan progres proyek.
A4: Task Group | B4: CRUD Task Group | C4: Sistem memungkinkan pengelolaan daftar grup task sebagai kategori dalam proyek.
A5: Task dan Subtask | B5: CRUD Task | C5: Task dapat dibuat dengan atribut dasar seperti durasi, prioritas, status, dan user yang ditugaskan.
B6: Update Progress | C6: Perubahan progres task langsung memengaruhi perhitungan EVM secara otomatis.
B7: Assign to Engineer | C7: Task dapat ditugaskan kepada pengguna tertentu dengan pilihan dari daftar user yang tersedia.
B8: CRUD Subtask | C8: Sistem mendukung pembuatan subtask dalam struktur hierarki sebagai bagian dari task utama.
B9: Parent Progress Sync | C9: Progres subtask secara otomatis memperbarui progres task induk.
A10: Dependencies | B10: Create FS Dependency | C10: Sistem mendukung pembuatan hubungan antar task (Finish-to-Start) untuk kebutuhan alur kerja.
B11: Auto Recalculate Schedule | C11: Perubahan durasi atau jadwal task akan mengupdate jadwal task terkait secara otomatis.
A12: Inventories | B12: CRUD Inventory | C12: Sistem mencatat dan mengelola daftar inventaris material dan alat dengan kuantitas dan kategori detail.
B13: Allocate Inventory | C13: Material dapat dialokasikan ke task dan setiap aktivitas dicatat otomatis dalam log sistem.
B14: Prevent Over-Allocation | C14: Sistem mencegah alokasi material melebihi stok yang tersedia.
A15: Work Report | B15: Submit Report | C15: User dapat mengirim laporan pekerjaan beserta lampiran foto sebagai bukti kegiatan lapangan.
B16: Auto Update Progress | C16: Laporan pekerjaan otomatis memengaruhi progres task dan perhitungan Earned Value.
E19: No | F19: Aspek Evaluasi | G19: Ulasan
E20: 1. | F20: Apa yang berjalan dengan baik? | G20: a) Semua fitur inti berjalan stabil tanpa error mayor dan memenuhi DoD. b) Perhitungan EVM otomatis menghasilkan nilai yang konsisten berdasarkan progres dan laporan pekerjaan. c) Integrasi antar modul (Task → Progress → EVM → Dashboard) sudah berjalan sinkron tanpa inkonsistensi data. d) Validasi input berjalan baik, termasuk pencegahan over-allocation dan circular dependency. e) Deployment ke environment staging berjalan mulus tanpa blocker.
E21: 2. | F21: Apa yang dapat diperbaiki? | G21: a) Beberapa alur form masih bisa diperhalus untuk meningkatkan pengalaman pengguna. b) Kalimat validasi masih terlalu teknis dan kurang ramah bagi user non-teknis. c) Tampilan visual progress EVM masih perlu penyempurnaan agar lebih mudah dipahami pada pandangan pertama. d) Dokumentasi API masih bisa diringkas agar lebih efisien bagi pengembang baru. e) Walkthrough onboarding pengguna belum tersedia dan dapat menjadi peningkatan pada sprint selanjutnya.
E22: 3. | F22: Tantangan yang dihadapi | G22: a) Sinkronisasi progres task terhadap perhitungan EVM memerlukan penyesuaian logic yang kompleks. b) Validasi edge-case seperti circular dependency memerlukan beberapa iterasi testing sebelum stabil. c) Alokasi inventory ke task perlu kontrol ketat agar tetap sinkron dengan stok utama. d) Manajemen integrasi antar modul memerlukan koordinasi lintas tim selama development berlangsung.
E23: 4. | F23: Pembelajaran yang didapat | G23: a) Implementasi validasi sejak awal sprint mengurangi rework dan mempercepat testing. b) Pendekatan modular pada EVM lebih efektif dibanding implementasi full dalam satu tahap. c) Dokumentasi paralel dengan development terbukti mempercepat debugging dan proses UAT. d) Rapat sinkronisasi kecil namun rutin membantu menjaga alignment antar modul.
E24: 5. | F24: Feedback dari stakeholder | G24: a) Stakeholder puas karena fitur inti dan fungsi EVM berjalan sesuai harapan tanpa revisi kritikal. b) Visualisasi progres dan indikator performa dianggap sudah baik, namun masih dapat dibuat lebih informatif. c) Stakeholder mengusulkan penambahan fitur otomatisasi notifikasi deadline di sprint berikutnya. d) Sistem dinilai sudah layak digunakan sebagai versi internal uji operasional.

Sheet Sheet12
A1: No | B1: Fitur | C1: User Story | D1: Estimasi | E1: Weight (%)
A2: 1. | B2: Realtime Update Progress | C2: Sebagai Project Manager, saya ingin melihat progres proyek secara real-time agar dapat memantau perkembangan tugas tanpa delay. | D2: 5 | E2: 0.25
A3: 2. | B3: Grafik Kurva S | C3: Sebagai Project Manager, saya ingin melihat grafik Kurva S proyek agar dapat memantau jadwal dan performa proyek secara visual. | D3: 5 | E3: 0.25
A4: 3. | B4: Alert dan Notifikasi | C4: Sebagai Team Member dan Project Manager, saya ingin menerima notifikasi agar dapat segera menindaklanjuti perubahan atau update penting. | D4: 5 | E4: 0.25
A5: 4. | B5: Testing dan UAT | C5: Sebagai QA dan Project Manager, saya ingin melakukan pengujian blackbox dan UAT pada Sprint 5 agar memastikan fitur berjalan sesuai kebutuhan pengguna. | D5: 5 | E5: 0.25
C6: Total | D6: 20 | E6: 1
A9: No | B9: Fitur | C9: User Story | D9: Estimasi | E9: Weight (%)
A10: 1. | B10: Settings Label Status Proyek | C10: Sebagai Project Manager, saya ingin mengatur label status proyek agar mudah memonitor progres proyek. | D10: 7 hari | E10: =7/41 -> 0.17073171
A11: 2. | B11: Upload Lampiran (Attachments) | C11: Sebagai Team Member, saya ingin mengunggah lampiran terkait tugas agar dokumentasi proyek lengkap. | D11: 7 hari | E11: =7/41 -> 0.17073171
A12: 3. | B12: Activity Logs | C12: Sebagai Project Manager, saya ingin melihat riwayat aktivitas sistem agar memantau perubahan dan tindakan pengguna. | D12: 7 hari | E12: =7/41 -> 0.17073171
A13: 4. | B13: Blackbox Test + UAT Sprint 6 | C13: Sebagai Administrator dan Project Manager, saya ingin melakukan pengujian blackbox dan UAT pada Sprint 6 agar fitur berjalan sesuai kebutuhan. | D13: 7 hari | E13: =7/41 -> 0.17073171
A14: 5. | B14: Dokumentasi Sistem dan User Manual | C14: Sebagai pengguna dan tim proyek, saya ingin memiliki dokumentasi dan manual agar mudah memahami penggunaan sistem. | D14: 7 hari | E14: =7/41 -> 0.17073171
A15: 6. | B15: Final Fixing dan Deployment | C15: Sebagai Project Manager, saya ingin melakukan perbaikan terakhir dan deployment agar sistem siap digunakan. | D15: 6 hari | E15: =6/41 -> 0.14634146
C16: Total | D16: 41 hari | E16: =SUM(E10:E15) -> 1

Sheet Sheet13
